odoo/addons/sale_numeric_step/README.rst
odoo/addons/sale_numeric_step/__init__.py
odoo/addons/sale_numeric_step/__manifest__.py
odoo/addons/sale_numeric_step/i18n/it.po
odoo/addons/sale_numeric_step/i18n/sale_numeric_step.pot
odoo/addons/sale_numeric_step/readme/CONTEXT.md
odoo/addons/sale_numeric_step/readme/CONTRIBUTORS.md
odoo/addons/sale_numeric_step/readme/CREDITS.md
odoo/addons/sale_numeric_step/readme/DESCRIPTION.md
odoo/addons/sale_numeric_step/readme/USAGE.md
odoo/addons/sale_numeric_step/static/description/icon.png
odoo/addons/sale_numeric_step/static/description/index.html
odoo/addons/sale_numeric_step/views/sale_order_view.xml
odoo_addon_sale_numeric_step-16.0.1.0.1.1.dist-info/METADATA
odoo_addon_sale_numeric_step-16.0.1.0.1.1.dist-info/WHEEL
odoo_addon_sale_numeric_step-16.0.1.0.1.1.dist-info/top_level.txt
odoo_addon_sale_numeric_step-16.0.1.0.1.1.dist-info/RECORD
